{
  "meta": {
    "n_clients": 300,
    "scale": 200.0,
    "horizon": 1440.0,
    "seed": 18
  },
  "depot": {
    "id": 0,
    "nom": "Dépôt",
    "x": 0.13436424411240122,
    "y": 0.8474337369372327,
    "a": 0.0,
    "b": null,
    "service": 0.0
  },
  "clients": [
    {
      "id": 1,
      "nom": "Ville 1",
      "x": 0.763774618976614,
      "y": 0.2550690257394217,
      "a": 873.1,
      "b": 1033.2,
      "service": 6.8
    },
    {
      "id": 2,
      "nom": "Ville 2",
      "x": 0.49543508709194095,
      "y": 0.4494910647887381,
      "a": 646.2,
      "b": 825.5,
      "service": 7.0
    },
    {
      "id": 3,
      "nom": "Ville 3",
      "x": 0.651592972722763,
      "y": 0.7887233511355132,
      "a": 605.0,
      "b": 756.7,
      "service": 9.8
    },
    {
      "id": 4,
      "nom": "Ville 4",
      "x": 0.0938595867742349,
      "y": 0.02834747652200631,
      "a": 913.3,
      "b": 1072.2,
      "service": 7.5
    },
    {
      "id": 5,
      "nom": "Ville 5",
      "x": 0.8357651039198697,
      "y": 0.43276706790505337,
      "a": 1039.1,
      "b": 1263.0,
      "service": 11.7
    },
    {
      "id": 6,
      "nom": "Ville 6",
      "x": 0.762280082457942,
      "y": 0.0021060533511106927,
      "a": 309.6,
      "b": 458.1,
      "service": 14.4
    },
    {
      "id": 7,
      "nom": "Ville 7",
      "x": 0.4453871940548014,
      "y": 0.7215400323407826,
      "a": 759.7,
      "b": 903.9,
      "service": 12.3
    },
    {
      "id": 8,
      "nom": "Ville 8",
      "x": 0.22876222127045265,
      "y": 0.9452706955539223,
      "a": 1152.7,
      "b": 1373.0,
      "service": 11.8
    },
    {
      "id": 9,
      "nom": "Ville 9",
      "x": 0.9014274576114836,
      "y": 0.030589983033553536,
      "a": 394.6,
      "b": 515.4,
      "service": 7.2
    },
    {
      "id": 10,
      "nom": "Ville 10",
      "x": 0.0254458609934608,
      "y": 0.5414124727934966,
      "a": 291.0,
      "b": 498.3,
      "service": 14.8
    },
    {
      "id": 11,
      "nom": "Ville 11",
      "x": 0.9391491627785106,
      "y": 0.38120423768821243,
      "a": 783.4,
      "b": 966.6,
      "service": 10.4
    },
    {
      "id": 12,
      "nom": "Ville 12",
      "x": 0.21659939713061338,
      "y": 0.4221165755827173,
      "a": 791.9,
      "b": 948.3,
      "service": 13.3
    },
    {
      "id": 13,
      "nom": "Ville 13",
      "x": 0.029040787574867943,
      "y": 0.22169166627303505,
      "a": 630.2,
      "b": 861.0,
      "service": 6.1
    },
    {
      "id": 14,
      "nom": "Ville 14",
      "x": 0.43788759365057206,
      "y": 0.49581224138185065,
      "a": 902.8,
      "b": 1098.5,
      "service": 6.5
    },
    {
      "id": 15,
      "nom": "Ville 15",
      "x": 0.23308445025757263,
      "y": 0.2308665415409843,
      "a": 273.0,
      "b": 475.3,
      "service": 6.6
    },
    {
      "id": 16,
      "nom": "Ville 16",
      "x": 0.2187810373376886,
      "y": 0.4596034657377336,
      "a": 537.3,
      "b": 714.9,
      "service": 9.4
    },
    {
      "id": 17,
      "nom": "Ville 17",
      "x": 0.28978161459048557,
      "y": 0.021489705265908876,
      "a": 930.1,
      "b": 1120.7,
      "service": 6.0
    },
    {
      "id": 18,
      "nom": "Ville 18",
      "x": 0.8375779756625729,
      "y": 0.5564543226524334,
      "a": 448.3,
      "b": 665.7,
      "service": 10.3
    },
    {
      "id": 19,
      "nom": "Ville 19",
      "x": 0.6422943629324456,
      "y": 0.1859062658947177,
      "a": 719.2,
      "b": 849.8,
      "service": 13.2
    },
    {
      "id": 20,
      "nom": "Ville 20",
      "x": 0.9925434121760651,
      "y": 0.8599465287952899,
      "a": 200.9,
      "b": 330.4,
      "service": 6.5
    },
    {
      "id": 21,
      "nom": "Ville 21",
      "x": 0.12088995980580641,
      "y": 0.3326951853601291,
      "a": 717.4,
      "b": 861.9,
      "service": 11.5
    },
    {
      "id": 22,
      "nom": "Ville 22",
      "x": 0.7214844075832684,
      "y": 0.7111917696952796,
      "a": 831.3,
      "b": 1046.4,
      "service": 14.1
    },
    {
      "id": 23,
      "nom": "Ville 23",
      "x": 0.9364405867994596,
      "y": 0.4221069999614152,
      "a": 899.6,
      "b": 1082.8,
      "service": 13.2
    },
    {
      "id": 24,
      "nom": "Ville 24",
      "x": 0.830035693274327,
      "y": 0.670305566414071,
      "a": 175.4,
      "b": 378.1,
      "service": 14.8
    },
    {
      "id": 25,
      "nom": "Ville 25",
      "x": 0.3033685109329176,
      "y": 0.5875806061435594,
      "a": 631.5,
      "b": 849.6,
      "service": 13.8
    },
    {
      "id": 26,
      "nom": "Ville 26",
      "x": 0.8824790008318577,
      "y": 0.8461974184283128,
      "a": 549.4,
      "b": 701.9,
      "service": 6.8
    },
    {
      "id": 27,
      "nom": "Ville 27",
      "x": 0.5052838205796004,
      "y": 0.5890022579825517,
      "a": 926.5,
      "b": 1063.7,
      "service": 9.0
    },
    {
      "id": 28,
      "nom": "Ville 28",
      "x": 0.034525830151341586,
      "y": 0.24273997354306764,
      "a": 1116.8,
      "b": 1273.0,
      "service": 8.4
    },
    {
      "id": 29,
      "nom": "Ville 29",
      "x": 0.7974042475543028,
      "y": 0.4143139993007743,
      "a": 1312.6,
      "b": 1440.0,
      "service": 6.3
    },
    {
      "id": 30,
      "nom": "Ville 30",
      "x": 0.17300740157905092,
      "y": 0.548798761388153,
      "a": 754.1,
      "b": 891.6,
      "service": 5.2
    },
    {
      "id": 31,
      "nom": "Ville 31",
      "x": 0.7030407620656315,
      "y": 0.6744858305023272,
      "a": 975.2,
      "b": 1173.5,
      "service": 6.6
    },
    {
      "id": 32,
      "nom": "Ville 32",
      "x": 0.3747030205016403,
      "y": 0.4389616300445631,
      "a": 679.0,
      "b": 866.0,
      "service": 9.3
    },
    {
      "id": 33,
      "nom": "Ville 33",
      "x": 0.5084264882499818,
      "y": 0.7784426150001458,
      "a": 133.6,
      "b": 345.8,
      "service": 9.6
    },
    {
      "id": 34,
      "nom": "Ville 34",
      "x": 0.5209384176131452,
      "y": 0.39325509496422606,
      "a": 557.0,
      "b": 725.5,
      "service": 12.7
    },
    {
      "id": 35,
      "nom": "Ville 35",
      "x": 0.4896935204622582,
      "y": 0.029574963966907064,
      "a": 623.0,
      "b": 792.8,
      "service": 11.1
    },
    {
      "id": 36,
      "nom": "Ville 36",
      "x": 0.04348729035652743,
      "y": 0.703382088603836,
      "a": 1194.5,
      "b": 1332.6,
      "service": 13.8
    },
    {
      "id": 37,
      "nom": "Ville 37",
      "x": 0.9831877173096739,
      "y": 0.5931837303800576,
      "a": 1035.6,
      "b": 1270.5,
      "service": 6.7
    },
    {
      "id": 38,
      "nom": "Ville 38",
      "x": 0.393599686377914,
      "y": 0.17034919685568128,
      "a": 391.9,
      "b": 518.9,
      "service": 12.3
    },
    {
      "id": 39,
      "nom": "Ville 39",
      "x": 0.5022385584334831,
      "y": 0.9820766375385342,
      "a": 1227.8,
      "b": 1438.8,
      "service": 13.3
    },
    {
      "id": 40,
      "nom": "Ville 40",
      "x": 0.7705231398308006,
      "y": 0.5396174484497788,
      "a": 1284.0,
      "b": 1440.0,
      "service": 12.4
    },
    {
      "id": 41,
      "nom": "Ville 41",
      "x": 0.8602897789205496,
      "y": 0.23217612806301458,
      "a": 346.2,
      "b": 475.4,
      "service": 14.3
    },
    {
      "id": 42,
      "nom": "Ville 42",
      "x": 0.513771663187637,
      "y": 0.9524673882682695,
      "a": 922.2,
      "b": 1137.8,
      "service": 13.4
    },
    {
      "id": 43,
      "nom": "Ville 43",
      "x": 0.5777948078012031,
      "y": 0.45913173191066836,
      "a": 396.1,
      "b": 586.6,
      "service": 6.3
    },
    {
      "id": 44,
      "nom": "Ville 44",
      "x": 0.2692794774414212,
      "y": 0.5479963094662489,
      "a": 433.6,
      "b": 626.0,
      "service": 5.6
    },
    {
      "id": 45,
      "nom": "Ville 45",
      "x": 0.9571162814602269,
      "y": 0.005709129450392925,
      "a": 949.5,
      "b": 1117.1,
      "service": 14.4
    },
    {
      "id": 46,
      "nom": "Ville 46",
      "x": 0.7836552326153898,
      "y": 0.8204859119254819,
      "a": 677.0,
      "b": 886.0,
      "service": 9.1
    },
    {
      "id": 47,
      "nom": "Ville 47",
      "x": 0.8861795808260082,
      "y": 0.7405034118331963,
      "a": 14.6,
      "b": 245.7,
      "service": 15.0
    },
    {
      "id": 48,
      "nom": "Ville 48",
      "x": 0.8091399008724796,
      "y": 0.518678283523002,
      "a": 60.3,
      "b": 211.1,
      "service": 13.0
    },
    {
      "id": 49,
      "nom": "Ville 49",
      "x": 0.561357864778379,
      "y": 0.4260906796881502,
      "a": 284.5,
      "b": 424.0,
      "service": 7.7
    },
    {
      "id": 50,
      "nom": "Ville 50",
      "x": 0.05612329752074041,
      "y": 0.8700101551766398,
      "a": 892.2,
      "b": 1064.7,
      "service": 6.4
    },
    {
      "id": 51,
      "nom": "Ville 51",
      "x": 0.5699993338763802,
      "y": 0.19983942017714307,
      "a": 1113.3,
      "b": 1333.5,
      "service": 6.1
    },
    {
      "id": 52,
      "nom": "Ville 52",
      "x": 0.5047204674288633,
      "y": 0.48492511222773416,
      "a": 1095.3,
      "b": 1308.4,
      "service": 7.6
    },
    {
      "id": 53,
      "nom": "Ville 53",
      "x": 0.3567899645449557,
      "y": 0.3460779190181549,
      "a": 116.0,
      "b": 321.1,
      "service": 10.3
    },
    {
      "id": 54,
      "nom": "Ville 54",
      "x": 0.5384787957378443,
      "y": 0.6234894527975051,
      "a": 1170.7,
      "b": 1404.7,
      "service": 13.7
    },
    {
      "id": 55,
      "nom": "Ville 55",
      "x": 0.6124524647827256,
      "y": 0.4581468000997244,
      "a": 1288.2,
      "b": 1419.4,
      "service": 6.6
    },
    {
      "id": 56,
      "nom": "Ville 56",
      "x": 0.027974984083842358,
      "y": 0.22960503127702392,
      "a": 711.4,
      "b": 908.1,
      "service": 8.6
    },
    {
      "id": 57,
      "nom": "Ville 57",
      "x": 0.1772112589385827,
      "y": 0.5844608707784413,
      "a": 1197.3,
      "b": 1410.2,
      "service": 10.3
    },
    {
      "id": 58,
      "nom": "Ville 58",
      "x": 0.8610088608533248,
      "y": 0.798438940577426,
      "a": 893.3,
      "b": 1068.0,
      "service": 13.6
    },
    {
      "id": 59,
      "nom": "Ville 59",
      "x": 0.7970975626354962,
      "y": 0.8164373705606909,
      "a": 854.0,
      "b": 1086.3,
      "service": 5.2
    },
    {
      "id": 60,
      "nom": "Ville 60",
      "x": 0.25529404008730594,
      "y": 0.841744832274096,
      "a": 1315.2,
      "b": 1437.3,
      "service": 6.9
    },
    {
      "id": 61,
      "nom": "Ville 61",
      "x": 0.6731135254387071,
      "y": 0.08323413780389788,
      "a": 991.2,
      "b": 1196.8,
      "service": 9.0
    },
    {
      "id": 62,
      "nom": "Ville 62",
      "x": 0.0166906301155596,
      "y": 0.014559974924812313,
      "a": 370.2,
      "b": 519.8,
      "service": 10.8
    },
    {
      "id": 63,
      "nom": "Ville 63",
      "x": 0.7555867752521982,
      "y": 0.2495592256534228,
      "a": 851.5,
      "b": 973.7,
      "service": 6.4
    },
    {
      "id": 64,
      "nom": "Ville 64",
      "x": 0.10948862729435938,
      "y": 0.6248020841524763,
      "a": 946.4,
      "b": 1120.0,
      "service": 6.3
    },
    {
      "id": 65,
      "nom": "Ville 65",
      "x": 0.3444228640964949,
      "y": 0.06951537853084733,
      "a": 560.2,
      "b": 791.2,
      "service": 5.2
    },
    {
      "id": 66,
      "nom": "Ville 66",
      "x": 0.1596255246938475,
      "y": 0.5273803990480128,
      "a": 354.4,
      "b": 490.8,
      "service": 10.1
    },
    {
      "id": 67,
      "nom": "Ville 67",
      "x": 0.16814494622242826,
      "y": 0.2729144368186801,
      "a": 320.0,
      "b": 473.0,
      "service": 10.0
    },
    {
      "id": 68,
      "nom": "Ville 68",
      "x": 0.7115899271852729,
      "y": 0.4547016300456639,
      "a": 800.2,
      "b": 1015.4,
      "service": 5.6
    },
    {
      "id": 69,
      "nom": "Ville 69",
      "x": 0.3220017663873259,
      "y": 0.4737710141702789,
      "a": 807.9,
      "b": 963.0,
      "service": 10.1
    },
    {
      "id": 70,
      "nom": "Ville 70",
      "x": 0.023634577631987064,
      "y": 0.38655710476146987,
      "a": 378.6,
      "b": 608.7,
      "service": 14.9
    },
    {
      "id": 71,
      "nom": "Ville 71",
      "x": 0.4209186792090759,
      "y": 0.18803930475131292,
      "a": 872.2,
      "b": 1096.6,
      "service": 5.1
    },
    {
      "id": 72,
      "nom": "Ville 72",
      "x": 0.10876169244541334,
      "y": 0.8998185003560202,
      "a": 285.1,
      "b": 425.2,
      "service": 10.7
    },
    {
      "id": 73,
      "nom": "Ville 73",
      "x": 0.5101159809286764,
      "y": 0.2090909925517701,
      "a": 1311.2,
      "b": 1440.0,
      "service": 14.9
    },
    {
      "id": 74,
      "nom": "Ville 74",
      "x": 0.6056486400340165,
      "y": 0.8170396683778869,
      "a": 1093.3,
      "b": 1317.4,
      "service": 9.1
    },
    {
      "id": 75,
      "nom": "Ville 75",
      "x": 0.020818108509287336,
      "y": 0.017864520827795327,
      "a": 719.3,
      "b": 869.2,
      "service": 5.3
    },
    {
      "id": 76,
      "nom": "Ville 76",
      "x": 0.146461740399346,
      "y": 0.7188354727617898,
      "a": 914.4,
      "b": 1092.8,
      "service": 5.8
    },
    {
      "id": 77,
      "nom": "Ville 77",
      "x": 0.16022759262970465,
      "y": 0.7046056278520025,
      "a": 1003.0,
      "b": 1161.7,
      "service": 7.1
    },
    {
      "id": 78,
      "nom": "Ville 78",
      "x": 0.6781757952769475,
      "y": 0.5447021635789044,
      "a": 394.4,
      "b": 537.9,
      "service": 7.6
    },
    {
      "id": 79,
      "nom": "Ville 79",
      "x": 0.22059974802267657,
      "y": 0.9755945178178834,
      "a": 435.0,
      "b": 666.9,
      "service": 13.4
    },
    {
      "id": 80,
      "nom": "Ville 80",
      "x": 0.797810857706151,
      "y": 0.516599516949393,
      "a": 711.3,
      "b": 938.7,
      "service": 11.9
    },
    {
      "id": 81,
      "nom": "Ville 81",
      "x": 0.22319578024667075,
      "y": 0.6485064180992564,
      "a": 46.7,
      "b": 245.4,
      "service": 8.7
    },
    {
      "id": 82,
      "nom": "Ville 82",
      "x": 0.3948980098582996,
      "y": 0.5758459627880567,
      "a": 1224.5,
      "b": 1440.0,
      "service": 5.6
    },
    {
      "id": 83,
      "nom": "Ville 83",
      "x": 0.32124580934512525,
      "y": 0.6309478612713469,
      "a": 118.6,
      "b": 353.5,
      "service": 8.9
    },
    {
      "id": 84,
      "nom": "Ville 84",
      "x": 0.058785116206491295,
      "y": 0.29860594962301334,
      "a": 1276.1,
      "b": 1440.0,
      "service": 7.6
    },
    {
      "id": 85,
      "nom": "Ville 85",
      "x": 0.9679033101508892,
      "y": 0.8755342442351592,
      "a": 1154.1,
      "b": 1292.4,
      "service": 13.9
    },
    {
      "id": 86,
      "nom": "Ville 86",
      "x": 0.30638662033324593,
      "y": 0.8585144063565593,
      "a": 569.0,
      "b": 713.0,
      "service": 8.3
    },
    {
      "id": 87,
      "nom": "Ville 87",
      "x": 0.31036362735313405,
      "y": 0.9392884321352825,
      "a": 276.8,
      "b": 425.1,
      "service": 14.3
    },
    {
      "id": 88,
      "nom": "Ville 88",
      "x": 0.7438421186671211,
      "y": 0.4161722627650255,
      "a": 199.7,
      "b": 417.3,
      "service": 6.8
    },
    {
      "id": 89,
      "nom": "Ville 89",
      "x": 0.25235810227983535,
      "y": 0.008480262463668842,
      "a": 777.9,
      "b": 913.0,
      "service": 7.0
    },
    {
      "id": 90,
      "nom": "Ville 90",
      "x": 0.8787178982088466,
      "y": 0.03791653059858058,
      "a": 1035.6,
      "b": 1268.7,
      "service": 13.1
    },
    {
      "id": 91,
      "nom": "Ville 91",
      "x": 0.8194141106127972,
      "y": 0.962201125180818,
      "a": 884.0,
      "b": 1091.2,
      "service": 5.6
    },
    {
      "id": 92,
      "nom": "Ville 92",
      "x": 0.5702805702451802,
      "y": 0.17151709517771863,
      "a": 909.7,
      "b": 1068.4,
      "service": 8.4
    },
    {
      "id": 93,
      "nom": "Ville 93",
      "x": 0.8677810644349934,
      "y": 0.9737752361596916,
      "a": 1124.9,
      "b": 1344.0,
      "service": 10.8
    },
    {
      "id": 94,
      "nom": "Ville 94",
      "x": 0.7040231423300713,
      "y": 0.5088737460778905,
      "a": 341.8,
      "b": 576.1,
      "service": 8.3
    },
    {
      "id": 95,
      "nom": "Ville 95",
      "x": 0.37796883434360806,
      "y": 0.34693088456262167,
      "a": 623.0,
      "b": 793.1,
      "service": 7.3
    },
    {
      "id": 96,
      "nom": "Ville 96",
      "x": 0.2057617572947047,
      "y": 0.6741530142468641,
      "a": 705.5,
      "b": 839.5,
      "service": 8.6
    },
    {
      "id": 97,
      "nom": "Ville 97",
      "x": 0.4329501211003163,
      "y": 0.1941186449851896,
      "a": 887.8,
      "b": 1109.6,
      "service": 9.7
    },
    {
      "id": 98,
      "nom": "Ville 98",
      "x": 0.10442422284151531,
      "y": 0.6659575282786826,
      "a": 304.4,
      "b": 458.3,
      "service": 9.9
    },
    {
      "id": 99,
      "nom": "Ville 99",
      "x": 0.29607267308315155,
      "y": 0.4997999222368016,
      "a": 193.6,
      "b": 350.4,
      "service": 6.9
    },
    {
      "id": 100,
      "nom": "Ville 100",
      "x": 0.3253456548759963,
      "y": 0.8716215074235552,
      "a": 1247.6,
      "b": 1440.0,
      "service": 8.8
    },
    {
      "id": 101,
      "nom": "Ville 101",
      "x": 0.8996782696347811,
      "y": 0.018092983640471738,
      "a": 649.1,
      "b": 792.3,
      "service": 14.2
    },
    {
      "id": 102,
      "nom": "Ville 102",
      "x": 0.2008530114407594,
      "y": 0.3277407050962675,
      "a": 919.6,
      "b": 1158.9,
      "service": 10.7
    },
    {
      "id": 103,
      "nom": "Ville 103",
      "x": 0.9870497179280261,
      "y": 0.7827003757293756,
      "a": 1006.5,
      "b": 1241.8,
      "service": 7.3
    },
    {
      "id": 104,
      "nom": "Ville 104",
      "x": 0.3390956478509337,
      "y": 0.21302979638081376,
      "a": 687.4,
      "b": 820.3,
      "service": 8.9
    },
    {
      "id": 105,
      "nom": "Ville 105",
      "x": 0.6744550697237632,
      "y": 0.8377010701539643,
      "a": 72.7,
      "b": 286.4,
      "service": 11.7
    },
    {
      "id": 106,
      "nom": "Ville 106",
      "x": 0.9321874718936273,
      "y": 0.3438498147908198,
      "a": 1097.0,
      "b": 1318.5,
      "service": 12.6
    },
    {
      "id": 107,
      "nom": "Ville 107",
      "x": 0.8823932024664636,
      "y": 0.6871101821536574,
      "a": 1156.5,
      "b": 1361.3,
      "service": 5.7
    },
    {
      "id": 108,
      "nom": "Ville 108",
      "x": 0.48449872261249405,
      "y": 0.9855082298257978,
      "a": 1188.4,
      "b": 1366.1,
      "service": 14.5
    },
    {
      "id": 109,
      "nom": "Ville 109",
      "x": 0.23464043487103847,
      "y": 0.7254651862412724,
      "a": 263.5,
      "b": 499.9,
      "service": 13.6
    },
    {
      "id": 110,
      "nom": "Ville 110",
      "x": 0.0846802304164842,
      "y": 0.16969414179438758,
      "a": 1071.9,
      "b": 1257.4,
      "service": 11.7
    },
    {
      "id": 111,
      "nom": "Ville 111",
      "x": 0.9109877835080679,
      "y": 0.21296819499142416,
      "a": 319.9,
      "b": 536.1,
      "service": 10.7
    },
    {
      "id": 112,
      "nom": "Ville 112",
      "x": 0.7591161827164402,
      "y": 0.6002088301322496,
      "a": 295.6,
      "b": 506.1,
      "service": 10.2
    },
    {
      "id": 113,
      "nom": "Ville 113",
      "x": 0.8411321957058551,
      "y": 0.3681079994056491,
      "a": 565.8,
      "b": 782.5,
      "service": 10.8
    },
    {
      "id": 114,
      "nom": "Ville 114",
      "x": 0.34028523500198804,
      "y": 0.29121528741113467,
      "a": 894.9,
      "b": 1080.0,
      "service": 9.2
    },
    {
      "id": 115,
      "nom": "Ville 115",
      "x": 0.8674198235869027,
      "y": 0.6039825288917112,
      "a": 467.6,
      "b": 658.3,
      "service": 8.7
    },
    {
      "id": 116,
      "nom": "Ville 116",
      "x": 0.9543074571721899,
      "y": 0.8872651047169627,
      "a": 227.2,
      "b": 385.0,
      "service": 6.8
    },
    {
      "id": 117,
      "nom": "Ville 117",
      "x": 0.13534597739545295,
      "y": 0.5511704740692165,
      "a": 247.8,
      "b": 460.1,
      "service": 12.1
    },
    {
      "id": 118,
      "nom": "Ville 118",
      "x": 0.1042749980146136,
      "y": 0.03913779859691058,
      "a": 1247.7,
      "b": 1380.7,
      "service": 8.3
    },
    {
      "id": 119,
      "nom": "Ville 119",
      "x": 0.07319341883234853,
      "y": 0.866168357366572,
      "a": 1087.8,
      "b": 1307.4,
      "service": 13.5
    },
    {
      "id": 120,
      "nom": "Ville 120",
      "x": 0.7881164487252263,
      "y": 0.8285059714691135,
      "a": 392.2,
      "b": 627.0,
      "service": 11.3
    },
    {
      "id": 121,
      "nom": "Ville 121",
      "x": 0.3408974641165834,
      "y": 0.6151860325590366,
      "a": 927.8,
      "b": 1096.6,
      "service": 7.2
    },
    {
      "id": 122,
      "nom": "Ville 122",
      "x": 0.7819036016327547,
      "y": 0.3780396288383874,
      "a": 547.2,
      "b": 705.3,
      "service": 5.7
    },
    {
      "id": 123,
      "nom": "Ville 123",
      "x": 0.5707815255990233,
      "y": 0.2237140727487692,
      "a": 272.4,
      "b": 491.7,
      "service": 12.9
    },
    {
      "id": 124,
      "nom": "Ville 124",
      "x": 0.08174326235239371,
      "y": 0.26672364298173634,
      "a": 114.3,
      "b": 309.0,
      "service": 5.3
    },
    {
      "id": 125,
      "nom": "Ville 125",
      "x": 0.8907681278553053,
      "y": 0.5644468332401974,
      "a": 811.7,
      "b": 951.2,
      "service": 14.3
    },
    {
      "id": 126,
      "nom": "Ville 126",
      "x": 0.9250672021084733,
      "y": 0.4577692590412453,
      "a": 888.0,
      "b": 1008.7,
      "service": 14.1
    },
    {
      "id": 127,
      "nom": "Ville 127",
      "x": 0.2771827661076983,
      "y": 0.7870146635603288,
      "a": 514.7,
      "b": 698.4,
      "service": 6.3
    },
    {
      "id": 128,
      "nom": "Ville 128",
      "x": 0.8277681566457297,
      "y": 0.012381744486666624,
      "a": 1105.0,
      "b": 1298.7,
      "service": 10.7
    },
    {
      "id": 129,
      "nom": "Ville 129",
      "x": 0.670411639023931,
      "y": 0.09168312261651779,
      "a": 535.5,
      "b": 696.1,
      "service": 14.6
    },
    {
      "id": 130,
      "nom": "Ville 130",
      "x": 0.1151024984279273,
      "y": 0.8850600703796611,
      "a": 1190.1,
      "b": 1361.8,
      "service": 11.6
    },
    {
      "id": 131,
      "nom": "Ville 131",
      "x": 0.04002353689016469,
      "y": 0.2396333648675093,
      "a": 500.8,
      "b": 645.3,
      "service": 5.5
    },
    {
      "id": 132,
      "nom": "Ville 132",
      "x": 0.9881584986060327,
      "y": 0.4210135874302673,
      "a": 433.1,
      "b": 607.7,
      "service": 14.0
    },
    {
      "id": 133,
      "nom": "Ville 133",
      "x": 0.1155581805922733,
      "y": 0.16738343746133177,
      "a": 75.3,
      "b": 206.1,
      "service": 11.2
    },
    {
      "id": 134,
      "nom": "Ville 134",
      "x": 0.24142028509784308,
      "y": 0.7440064165370084,
      "a": 332.4,
      "b": 459.7,
      "service": 10.2
    },
    {
      "id": 135,
      "nom": "Ville 135",
      "x": 0.1028341459863098,
      "y": 0.9107644182793333,
      "a": 970.7,
      "b": 1164.4,
      "service": 12.4
    },
    {
      "id": 136,
      "nom": "Ville 136",
      "x": 0.3782772705442261,
      "y": 0.9702640365282106,
      "a": 1075.3,
      "b": 1314.7,
      "service": 6.3
    },
    {
      "id": 137,
      "nom": "Ville 137",
      "x": 0.9092227281507113,
      "y": 0.29402358494854774,
      "a": 898.6,
      "b": 1024.8,
      "service": 6.1
    },
    {
      "id": 138,
      "nom": "Ville 138",
      "x": 0.2534101360411267,
      "y": 0.47701009597226784,
      "a": 439.8,
      "b": 675.9,
      "service": 6.1
    },
    {
      "id": 139,
      "nom": "Ville 139",
      "x": 0.10012914395045203,
      "y": 0.6520501994894172,
      "a": 713.0,
      "b": 939.4,
      "service": 9.6
    },
    {
      "id": 140,
      "nom": "Ville 140",
      "x": 0.039620213413704475,
      "y": 0.010506151518672291,
      "a": 381.9,
      "b": 511.7,
      "service": 8.9
    },
    {
      "id": 141,
      "nom": "Ville 141",
      "x": 0.9825836265504634,
      "y": 0.2955498600489178,
      "a": 808.8,
      "b": 1034.9,
      "service": 7.3
    },
    {
      "id": 142,
      "nom": "Ville 142",
      "x": 0.5965706431884413,
      "y": 0.44984453463009777,
      "a": 346.2,
      "b": 546.4,
      "service": 14.9
    },
    {
      "id": 143,
      "nom": "Ville 143",
      "x": 0.31328086106892794,
      "y": 0.06296479004764532,
      "a": 737.4,
      "b": 859.3,
      "service": 8.2
    },
    {
      "id": 144,
      "nom": "Ville 144",
      "x": 0.9133920171659404,
      "y": 0.9698132768381156,
      "a": 1030.0,
      "b": 1240.9,
      "service": 14.3
    },
    {
      "id": 145,
      "nom": "Ville 145",
      "x": 0.9697965044964699,
      "y": 0.1113623101268919,
      "a": 502.6,
      "b": 723.6,
      "service": 11.4
    },
    {
      "id": 146,
      "nom": "Ville 146",
      "x": 0.21519327003609845,
      "y": 0.6178068800115557,
      "a": 875.5,
      "b": 1028.0,
      "service": 10.1
    },
    {
      "id": 147,
      "nom": "Ville 147",
      "x": 0.979952885890077,
      "y": 0.5429131974847156,
      "a": 948.0,
      "b": 1105.9,
      "service": 6.8
    },
    {
      "id": 148,
      "nom": "Ville 148",
      "x": 0.6881898080477126,
      "y": 0.6618344288753493,
      "a": 396.4,
      "b": 567.0,
      "service": 5.4
    },
    {
      "id": 149,
      "nom": "Ville 149",
      "x": 0.259085991853645,
      "y": 0.5416022629129655,
      "a": 184.1,
      "b": 389.8,
      "service": 6.9
    },
    {
      "id": 150,
      "nom": "Ville 150",
      "x": 0.3073211178125135,
      "y": 0.24638119608509224,
      "a": 666.6,
      "b": 872.5,
      "service": 9.6
    },
    {
      "id": 151,
      "nom": "Ville 151",
      "x": 0.08136876538378779,
      "y": 0.2807867235646755,
      "a": 681.6,
      "b": 919.9,
      "service": 5.5
    },
    {
      "id": 152,
      "nom": "Ville 152",
      "x": 0.9833767172194025,
      "y": 0.4479022405332955,
      "a": 925.2,
      "b": 1066.6,
      "service": 7.8
    },
    {
      "id": 153,
      "nom": "Ville 153",
      "x": 0.6520105345126705,
      "y": 0.6434660802698416,
      "a": 592.6,
      "b": 738.7,
      "service": 8.8
    },
    {
      "id": 154,
      "nom": "Ville 154",
      "x": 0.940734522249,
      "y": 0.39047855113892316,
      "a": 437.8,
      "b": 614.6,
      "service": 7.4
    },
    {
      "id": 155,
      "nom": "Ville 155",
      "x": 0.3067842948515136,
      "y": 0.3272414146871332,
      "a": 652.9,
      "b": 802.8,
      "service": 8.9
    },
    {
      "id": 156,
      "nom": "Ville 156",
      "x": 0.3167351468856021,
      "y": 0.847134765826215,
      "a": 1012.9,
      "b": 1189.3,
      "service": 10.4
    },
    {
      "id": 157,
      "nom": "Ville 157",
      "x": 0.893500245521601,
      "y": 0.3028093296725163,
      "a": 1084.4,
      "b": 1279.5,
      "service": 8.6
    },
    {
      "id": 158,
      "nom": "Ville 158",
      "x": 0.33433340565076186,
      "y": 0.5442254141821842,
      "a": 408.7,
      "b": 643.5,
      "service": 10.0
    },
    {
      "id": 159,
      "nom": "Ville 159",
      "x": 0.5789854363170839,
      "y": 0.5959625400010043,
      "a": 1218.6,
      "b": 1375.3,
      "service": 6.2
    },
    {
      "id": 160,
      "nom": "Ville 160",
      "x": 0.2450980038952486,
      "y": 0.020374028446252357,
      "a": 59.5,
      "b": 262.8,
      "service": 14.2
    },
    {
      "id": 161,
      "nom": "Ville 161",
      "x": 0.24375929982791578,
      "y": 0.07232753387141089,
      "a": 810.8,
      "b": 941.3,
      "service": 9.8
    },
    {
      "id": 162,
      "nom": "Ville 162",
      "x": 0.551204754915506,
      "y": 0.07091636753953445,
      "a": 480.1,
      "b": 667.2,
      "service": 8.8
    },
    {
      "id": 163,
      "nom": "Ville 163",
      "x": 0.07512979225452299,
      "y": 0.6353820935630572,
      "a": 1254.4,
      "b": 1409.4,
      "service": 12.2
    },
    {
      "id": 164,
      "nom": "Ville 164",
      "x": 0.2908215504193956,
      "y": 0.7921847578822924,
      "a": 241.5,
      "b": 471.4,
      "service": 5.5
    },
    {
      "id": 165,
      "nom": "Ville 165",
      "x": 0.49326104275013793,
      "y": 0.8626489777797094,
      "a": 880.6,
      "b": 1120.2,
      "service": 10.5
    },
    {
      "id": 166,
      "nom": "Ville 166",
      "x": 0.15417959616284405,
      "y": 0.5014295859466933,
      "a": 778.3,
      "b": 991.6,
      "service": 12.9
    },
    {
      "id": 167,
      "nom": "Ville 167",
      "x": 0.794983493746024,
      "y": 0.0771069862639161,
      "a": 1083.0,
      "b": 1223.9,
      "service": 6.7
    },
    {
      "id": 168,
      "nom": "Ville 168",
      "x": 0.9492279489729363,
      "y": 0.1732421083716036,
      "a": 1123.3,
      "b": 1311.7,
      "service": 13.8
    },
    {
      "id": 169,
      "nom": "Ville 169",
      "x": 0.7762089829859355,
      "y": 0.9848958711440725,
      "a": 165.8,
      "b": 344.3,
      "service": 7.8
    },
    {
      "id": 170,
      "nom": "Ville 170",
      "x": 0.8215501447435144,
      "y": 0.3197840027930057,
      "a": 485.0,
      "b": 623.0,
      "service": 7.1
    },
    {
      "id": 171,
      "nom": "Ville 171",
      "x": 0.1068777345815598,
      "y": 0.5143582510552492,
      "a": 1044.7,
      "b": 1258.8,
      "service": 5.8
    },
    {
      "id": 172,
      "nom": "Ville 172",
      "x": 0.919356939210688,
      "y": 0.29348949437066774,
      "a": 822.6,
      "b": 1040.6,
      "service": 10.9
    },
    {
      "id": 173,
      "nom": "Ville 173",
      "x": 0.8937587976957898,
      "y": 0.14168064702669492,
      "a": 836.7,
      "b": 963.4,
      "service": 10.9
    },
    {
      "id": 174,
      "nom": "Ville 174",
      "x": 0.9104816743927341,
      "y": 0.03175994589733666,
      "a": 913.5,
      "b": 1098.6,
      "service": 5.8
    },
    {
      "id": 175,
      "nom": "Ville 175",
      "x": 0.3160686777608829,
      "y": 0.9030882837141124,
      "a": 1068.2,
      "b": 1243.6,
      "service": 7.8
    },
    {
      "id": 176,
      "nom": "Ville 176",
      "x": 0.8038562809839719,
      "y": 0.9071537669967973,
      "a": 1264.6,
      "b": 1438.1,
      "service": 10.8
    },
    {
      "id": 177,
      "nom": "Ville 177",
      "x": 0.8407185222467378,
      "y": 0.7461848854045222,
      "a": 654.5,
      "b": 854.3,
      "service": 13.9
    },
    {
      "id": 178,
      "nom": "Ville 178",
      "x": 0.6895951793002646,
      "y": 0.1781548656443236,
      "a": 673.5,
      "b": 857.5,
      "service": 12.4
    },
    {
      "id": 179,
      "nom": "Ville 179",
      "x": 0.43263800097623695,
      "y": 0.15789694375216057,
      "a": 1007.7,
      "b": 1201.1,
      "service": 13.6
    },
    {
      "id": 180,
      "nom": "Ville 180",
      "x": 0.7148244519688113,
      "y": 0.667778739685542,
      "a": 341.8,
      "b": 528.6,
      "service": 12.1
    },
    {
      "id": 181,
      "nom": "Ville 181",
      "x": 0.2525864077938834,
      "y": 0.0644141933476613,
      "a": 951.9,
      "b": 1183.4,
      "service": 13.4
    },
    {
      "id": 182,
      "nom": "Ville 182",
      "x": 0.9633858833215757,
      "y": 0.8082526283723965,
      "a": 220.4,
      "b": 367.3,
      "service": 5.5
    },
    {
      "id": 183,
      "nom": "Ville 183",
      "x": 0.5492699313925192,
      "y": 0.5413776519849807,
      "a": 1186.1,
      "b": 1338.6,
      "service": 14.5
    },
    {
      "id": 184,
      "nom": "Ville 184",
      "x": 0.8512926663313799,
      "y": 0.45330967762221785,
      "a": 439.7,
      "b": 659.3,
      "service": 5.7
    },
    {
      "id": 185,
      "nom": "Ville 185",
      "x": 0.39571044472076744,
      "y": 0.33866914489505884,
      "a": 822.3,
      "b": 1054.9,
      "service": 13.4
    },
    {
      "id": 186,
      "nom": "Ville 186",
      "x": 0.2579690924717717,
      "y": 0.024408502825104206,
      "a": 16.1,
      "b": 157.0,
      "service": 12.7
    },
    {
      "id": 187,
      "nom": "Ville 187",
      "x": 0.6464388440000969,
      "y": 0.4166838822984099,
      "a": 1009.5,
      "b": 1233.7,
      "service": 13.3
    },
    {
      "id": 188,
      "nom": "Ville 188",
      "x": 0.5706036315777225,
      "y": 0.062321630803521044,
      "a": 1207.7,
      "b": 1327.7,
      "service": 10.9
    },
    {
      "id": 189,
      "nom": "Ville 189",
      "x": 0.3549434436862958,
      "y": 0.13828411395509788,
      "a": 50.6,
      "b": 288.5,
      "service": 8.8
    },
    {
      "id": 190,
      "nom": "Ville 190",
      "x": 0.12512901528549036,
      "y": 0.259112968915828,
      "a": 862.6,
      "b": 1048.4,
      "service": 13.7
    },
    {
      "id": 191,
      "nom": "Ville 191",
      "x": 0.8289343809851581,
      "y": 0.39779731306487276,
      "a": 771.3,
      "b": 925.3,
      "service": 10.2
    },
    {
      "id": 192,
      "nom": "Ville 192",
      "x": 0.40108215192090135,
      "y": 0.612444922992939,
      "a": 1119.8,
      "b": 1339.2,
      "service": 6.1
    },
    {
      "id": 193,
      "nom": "Ville 193",
      "x": 0.23352965329584996,
      "y": 0.007477173042134244,
      "a": 566.7,
      "b": 736.3,
      "service": 7.7
    },
    {
      "id": 194,
      "nom": "Ville 194",
      "x": 0.5287017398867132,
      "y": 0.5008996195572266,
      "a": 448.0,
      "b": 649.0,
      "service": 12.6
    },
    {
      "id": 195,
      "nom": "Ville 195",
      "x": 0.6488395923408533,
      "y": 0.4383169556417158,
      "a": 1216.0,
      "b": 1415.7,
      "service": 6.2
    },
    {
      "id": 196,
      "nom": "Ville 196",
      "x": 0.6865131306582006,
      "y": 0.7314219491610718,
      "a": 672.3,
      "b": 874.7,
      "service": 8.8
    },
    {
      "id": 197,
      "nom": "Ville 197",
      "x": 0.23837467516202382,
      "y": 0.4950722507160109,
      "a": 172.6,
      "b": 311.4,
      "service": 10.6
    },
    {
      "id": 198,
      "nom": "Ville 198",
      "x": 0.47882688758179337,
      "y": 0.225062085038767,
      "a": 834.6,
      "b": 1074.5,
      "service": 6.0
    },
    {
      "id": 199,
      "nom": "Ville 199",
      "x": 0.4122461329173408,
      "y": 0.560407434487989,
      "a": 1135.2,
      "b": 1347.2,
      "service": 6.2
    },
    {
      "id": 200,
      "nom": "Ville 200",
      "x": 0.9069395045058483,
      "y": 0.9177065838382222,
      "a": 618.6,
      "b": 748.5,
      "service": 7.6
    },
    {
      "id": 201,
      "nom": "Ville 201",
      "x": 0.27522536346579907,
      "y": 0.6464151756425885,
      "a": 617.0,
      "b": 837.3,
      "service": 13.1
    },
    {
      "id": 202,
      "nom": "Ville 202",
      "x": 0.0481973433614038,
      "y": 0.07155138822789708,
      "a": 576.6,
      "b": 762.1,
      "service": 9.2
    },
    {
      "id": 203,
      "nom": "Ville 203",
      "x": 0.5116917092002066,
      "y": 0.877424078946487,
      "a": 753.7,
      "b": 951.5,
      "service": 12.9
    },
    {
      "id": 204,
      "nom": "Ville 204",
      "x": 0.15946773075783105,
      "y": 0.7660278587973122,
      "a": 253.3,
      "b": 402.1,
      "service": 9.1
    },
    {
      "id": 205,
      "nom": "Ville 205",
      "x": 0.8830095693755464,
      "y": 0.3118020318353023,
      "a": 22.3,
      "b": 239.5,
      "service": 13.2
    },
    {
      "id": 206,
      "nom": "Ville 206",
      "x": 0.6925569646028146,
      "y": 0.8489911224865752,
      "a": 464.2,
      "b": 638.9,
      "service": 10.4
    },
    {
      "id": 207,
      "nom": "Ville 207",
      "x": 0.3716143307475649,
      "y": 0.7012826629078087,
      "a": 952.7,
      "b": 1160.6,
      "service": 9.1
    },
    {
      "id": 208,
      "nom": "Ville 208",
      "x": 0.7364181165753182,
      "y": 0.5945778048409015,
      "a": 635.2,
      "b": 831.8,
      "service": 14.2
    },
    {
      "id": 209,
      "nom": "Ville 209",
      "x": 0.8562771389130047,
      "y": 0.8966043711163488,
      "a": 921.5,
      "b": 1043.7,
      "service": 6.9
    },
    {
      "id": 210,
      "nom": "Ville 210",
      "x": 0.9600788169648591,
      "y": 0.5712326942175455,
      "a": 1213.7,
      "b": 1386.9,
      "service": 13.5
    },
    {
      "id": 211,
      "nom": "Ville 211",
      "x": 0.17627589520647535,
      "y": 0.2505954088773793,
      "a": 236.7,
      "b": 429.2,
      "service": 6.2
    },
    {
      "id": 212,
      "nom": "Ville 212",
      "x": 0.21761868850658306,
      "y": 0.5695173495977943,
      "a": 413.2,
      "b": 533.7,
      "service": 5.1
    },
    {
      "id": 213,
      "nom": "Ville 213",
      "x": 0.7577501146664367,
      "y": 0.05213322114218644,
      "a": 136.9,
      "b": 368.4,
      "service": 5.7
    },
    {
      "id": 214,
      "nom": "Ville 214",
      "x": 0.6816364556074682,
      "y": 0.7171532633675107,
      "a": 607.4,
      "b": 811.0,
      "service": 12.7
    },
    {
      "id": 215,
      "nom": "Ville 215",
      "x": 0.3479815079568077,
      "y": 0.5150558042933419,
      "a": 949.0,
      "b": 1097.8,
      "service": 6.1
    },
    {
      "id": 216,
      "nom": "Ville 216",
      "x": 0.16479815203117487,
      "y": 0.7298961504869986,
      "a": 495.9,
      "b": 719.0,
      "service": 12.0
    },
    {
      "id": 217,
      "nom": "Ville 217",
      "x": 0.040708687336548866,
      "y": 0.981221058148159,
      "a": 83.0,
      "b": 308.4,
      "service": 5.6
    },
    {
      "id": 218,
      "nom": "Ville 218",
      "x": 0.8079437334476703,
      "y": 0.6284485019821408,
      "a": 449.7,
      "b": 584.9,
      "service": 13.3
    },
    {
      "id": 219,
      "nom": "Ville 219",
      "x": 0.2675262446471117,
      "y": 0.9128628900924319,
      "a": 667.2,
      "b": 835.9,
      "service": 10.4
    },
    {
      "id": 220,
      "nom": "Ville 220",
      "x": 0.9594388378770715,
      "y": 0.13912615902147096,
      "a": 114.2,
      "b": 280.7,
      "service": 13.3
    },
    {
      "id": 221,
      "nom": "Ville 221",
      "x": 0.7757572503157156,
      "y": 0.8419308585435238,
      "a": 664.3,
      "b": 835.7,
      "service": 11.4
    },
    {
      "id": 222,
      "nom": "Ville 222",
      "x": 0.6597173563139825,
      "y": 0.7004077664167305,
      "a": 229.6,
      "b": 410.5,
      "service": 11.1
    },
    {
      "id": 223,
      "nom": "Ville 223",
      "x": 0.44505873211451163,
      "y": 0.9243078026249281,
      "a": 351.4,
      "b": 476.0,
      "service": 5.5
    },
    {
      "id": 224,
      "nom": "Ville 224",
      "x": 0.9712075281962813,
      "y": 0.3823533128201745,
      "a": 53.4,
      "b": 292.8,
      "service": 7.8
    },
    {
      "id": 225,
      "nom": "Ville 225",
      "x": 0.8027115308003568,
      "y": 0.4329215913805363,
      "a": 49.5,
      "b": 185.5,
      "service": 14.4
    },
    {
      "id": 226,
      "nom": "Ville 226",
      "x": 0.16475421868327378,
      "y": 0.32546727685726395,
      "a": 1255.1,
      "b": 1440.0,
      "service": 14.3
    },
    {
      "id": 227,
      "nom": "Ville 227",
      "x": 0.1263300748348425,
      "y": 0.9088847599027046,
      "a": 689.9,
      "b": 929.1,
      "service": 14.9
    },
    {
      "id": 228,
      "nom": "Ville 228",
      "x": 0.9594240800441438,
      "y": 0.11918673240587485,
      "a": 394.9,
      "b": 574.5,
      "service": 14.7
    },
    {
      "id": 229,
      "nom": "Ville 229",
      "x": 0.6006790811870585,
      "y": 0.40822409770858314,
      "a": 1271.6,
      "b": 1440.0,
      "service": 9.9
    },
    {
      "id": 230,
      "nom": "Ville 230",
      "x": 0.11809003100178916,
      "y": 0.295475514811817,
      "a": 1032.6,
      "b": 1193.5,
      "service": 8.3
    },
    {
      "id": 231,
      "nom": "Ville 231",
      "x": 0.2482163710806481,
      "y": 0.7495768111897567,
      "a": 405.8,
      "b": 578.2,
      "service": 11.1
    },
    {
      "id": 232,
      "nom": "Ville 232",
      "x": 0.004008955954045934,
      "y": 0.18983870393308366,
      "a": 93.1,
      "b": 294.7,
      "service": 10.2
    },
    {
      "id": 233,
      "nom": "Ville 233",
      "x": 0.43877307011993694,
      "y": 0.02103467308587126,
      "a": 70.2,
      "b": 215.6,
      "service": 13.5
    },
    {
      "id": 234,
      "nom": "Ville 234",
      "x": 0.6275265885374804,
      "y": 0.6056275385785042,
      "a": 460.2,
      "b": 585.0,
      "service": 11.2
    },
    {
      "id": 235,
      "nom": "Ville 235",
      "x": 0.8353323508828638,
      "y": 0.20660581568518466,
      "a": 270.5,
      "b": 505.3,
      "service": 7.9
    },
    {
      "id": 236,
      "nom": "Ville 236",
      "x": 0.2847816135615888,
      "y": 0.5423394307527486,
      "a": 120.4,
      "b": 296.1,
      "service": 12.7
    },
    {
      "id": 237,
      "nom": "Ville 237",
      "x": 0.2732256972129319,
      "y": 0.585738083402959,
      "a": 513.2,
      "b": 664.1,
      "service": 13.7
    },
    {
      "id": 238,
      "nom": "Ville 238",
      "x": 0.25088222945000915,
      "y": 0.6835271525859573,
      "a": 512.6,
      "b": 730.9,
      "service": 7.3
    },
    {
      "id": 239,
      "nom": "Ville 239",
      "x": 0.7910907183680019,
      "y": 0.8086546201638074,
      "a": 1292.5,
      "b": 1440.0,
      "service": 14.8
    },
    {
      "id": 240,
      "nom": "Ville 240",
      "x": 0.9736161095498469,
      "y": 0.5453770038258688,
      "a": 867.1,
      "b": 1065.8,
      "service": 5.4
    },
    {
      "id": 241,
      "nom": "Ville 241",
      "x": 0.49080927982901434,
      "y": 0.8556976997986436,
      "a": 41.5,
      "b": 219.4,
      "service": 6.3
    },
    {
      "id": 242,
      "nom": "Ville 242",
      "x": 0.7690673858593793,
      "y": 0.5705446293870352,
      "a": 1154.2,
      "b": 1357.2,
      "service": 8.1
    },
    {
      "id": 243,
      "nom": "Ville 243",
      "x": 0.3832563847662638,
      "y": 0.2840474457335592,
      "a": 1037.6,
      "b": 1160.2,
      "service": 8.8
    },
    {
      "id": 244,
      "nom": "Ville 244",
      "x": 0.10813920873416805,
      "y": 0.8075490893732804,
      "a": 361.2,
      "b": 515.6,
      "service": 10.3
    },
    {
      "id": 245,
      "nom": "Ville 245",
      "x": 0.11807153053066555,
      "y": 0.7472652346880435,
      "a": 895.5,
      "b": 1129.8,
      "service": 10.6
    },
    {
      "id": 246,
      "nom": "Ville 246",
      "x": 0.545287089768146,
      "y": 0.9649453287863279,
      "a": 280.8,
      "b": 510.7,
      "service": 10.0
    },
    {
      "id": 247,
      "nom": "Ville 247",
      "x": 0.7610656598531885,
      "y": 0.9735197845800538,
      "a": 1137.3,
      "b": 1321.2,
      "service": 13.4
    },
    {
      "id": 248,
      "nom": "Ville 248",
      "x": 0.13659401293980755,
      "y": 0.5003714738318865,
      "a": 1006.2,
      "b": 1137.4,
      "service": 5.0
    },
    {
      "id": 249,
      "nom": "Ville 249",
      "x": 0.5725782871654547,
      "y": 0.3112514573124735,
      "a": 273.6,
      "b": 480.6,
      "service": 9.6
    },
    {
      "id": 250,
      "nom": "Ville 250",
      "x": 0.5030324882064976,
      "y": 0.35681876360334597,
      "a": 1224.5,
      "b": 1440.0,
      "service": 9.4
    },
    {
      "id": 251,
      "nom": "Ville 251",
      "x": 0.5283939713514435,
      "y": 0.0008447179488895173,
      "a": 356.4,
      "b": 562.6,
      "service": 8.1
    },
    {
      "id": 252,
      "nom": "Ville 252",
      "x": 0.4423143321124289,
      "y": 0.4495521437392589,
      "a": 1238.5,
      "b": 1419.4,
      "service": 13.9
    },
    {
      "id": 253,
      "nom": "Ville 253",
      "x": 0.3047991882212113,
      "y": 0.3994027475965406,
      "a": 283.2,
      "b": 495.7,
      "service": 7.8
    },
    {
      "id": 254,
      "nom": "Ville 254",
      "x": 0.7830873111719908,
      "y": 0.6834128839628029,
      "a": 1096.4,
      "b": 1332.4,
      "service": 8.3
    },
    {
      "id": 255,
      "nom": "Ville 255",
      "x": 0.4922991328917098,
      "y": 0.6476682418421831,
      "a": 709.5,
      "b": 944.1,
      "service": 11.9
    },
    {
      "id": 256,
      "nom": "Ville 256",
      "x": 0.377558211851013,
      "y": 0.20391405043667976,
      "a": 805.7,
      "b": 999.2,
      "service": 12.3
    },
    {
      "id": 257,
      "nom": "Ville 257",
      "x": 0.003875657877555727,
      "y": 0.27762125160942186,
      "a": 403.5,
      "b": 531.1,
      "service": 10.3
    },
    {
      "id": 258,
      "nom": "Ville 258",
      "x": 0.598164198713661,
      "y": 0.8816629330706961,
      "a": 85.4,
      "b": 257.1,
      "service": 11.4
    },
    {
      "id": 259,
      "nom": "Ville 259",
      "x": 0.8294212499885301,
      "y": 0.5109602078711931,
      "a": 1034.1,
      "b": 1235.5,
      "service": 8.7
    },
    {
      "id": 260,
      "nom": "Ville 260",
      "x": 0.987018145049427,
      "y": 0.46158097386980335,
      "a": 795.2,
      "b": 976.3,
      "service": 13.8
    },
    {
      "id": 261,
      "nom": "Ville 261",
      "x": 0.8345934861668383,
      "y": 0.4089653412809712,
      "a": 383.3,
      "b": 552.6,
      "service": 7.4
    },
    {
      "id": 262,
      "nom": "Ville 262",
      "x": 0.7446306177387316,
      "y": 0.9875916912226816,
      "a": 616.3,
      "b": 758.8,
      "service": 10.3
    },
    {
      "id": 263,
      "nom": "Ville 263",
      "x": 0.30533659236797617,
      "y": 0.17031282521328428,
      "a": 1117.2,
      "b": 1310.9,
      "service": 7.6
    },
    {
      "id": 264,
      "nom": "Ville 264",
      "x": 0.6200337087276608,
      "y": 0.5309561803740346,
      "a": 391.0,
      "b": 549.8,
      "service": 7.0
    },
    {
      "id": 265,
      "nom": "Ville 265",
      "x": 0.359422031985154,
      "y": 0.003519242097051234,
      "a": 892.4,
      "b": 1073.5,
      "service": 5.9
    },
    {
      "id": 266,
      "nom": "Ville 266",
      "x": 0.3891626416098043,
      "y": 0.4258694721036601,
      "a": 1036.4,
      "b": 1234.2,
      "service": 9.3
    },
    {
      "id": 267,
      "nom": "Ville 267",
      "x": 0.405252071738319,
      "y": 0.8612453089775505,
      "a": 1135.3,
      "b": 1336.6,
      "service": 11.6
    },
    {
      "id": 268,
      "nom": "Ville 268",
      "x": 0.5844280270821319,
      "y": 0.7338307924531678,
      "a": 1143.2,
      "b": 1379.3,
      "service": 5.9
    },
    {
      "id": 269,
      "nom": "Ville 269",
      "x": 0.8979091716371104,
      "y": 0.7487734635751375,
      "a": 101.8,
      "b": 325.0,
      "service": 13.2
    },
    {
      "id": 270,
      "nom": "Ville 270",
      "x": 0.4927020519050469,
      "y": 0.7457683402868462,
      "a": 565.3,
      "b": 768.3,
      "service": 12.0
    },
    {
      "id": 271,
      "nom": "Ville 271",
      "x": 0.6403554004952637,
      "y": 0.6487454346633404,
      "a": 1122.0,
      "b": 1323.6,
      "service": 10.2
    },
    {
      "id": 272,
      "nom": "Ville 272",
      "x": 0.6296753586886549,
      "y": 0.4069989749884928,
      "a": 977.4,
      "b": 1151.8,
      "service": 12.6
    },
    {
      "id": 273,
      "nom": "Ville 273",
      "x": 0.6292620312875881,
      "y": 0.6337325109456275,
      "a": 755.5,
      "b": 934.1,
      "service": 5.0
    },
    {
      "id": 274,
      "nom": "Ville 274",
      "x": 0.9371179595389777,
      "y": 0.782473685370823,
      "a": 1017.0,
      "b": 1218.8,
      "service": 11.2
    },
    {
      "id": 275,
      "nom": "Ville 275",
      "x": 0.8462680666010907,
      "y": 0.7674997901425722,
      "a": 359.6,
      "b": 495.8,
      "service": 6.7
    },
    {
      "id": 276,
      "nom": "Ville 276",
      "x": 0.8153258619910289,
      "y": 0.6054623947302108,
      "a": 176.4,
      "b": 309.5,
      "service": 13.9
    },
    {
      "id": 277,
      "nom": "Ville 277",
      "x": 0.3494500883866837,
      "y": 0.26458325831813634,
      "a": 845.1,
      "b": 1051.6,
      "service": 14.7
    },
    {
      "id": 278,
      "nom": "Ville 278",
      "x": 0.7080200270648295,
      "y": 0.8739420748131903,
      "a": 41.9,
      "b": 228.1,
      "service": 15.0
    },
    {
      "id": 279,
      "nom": "Ville 279",
      "x": 0.5442467578028801,
      "y": 0.1520699669575002,
      "a": 1085.3,
      "b": 1216.3,
      "service": 8.5
    },
    {
      "id": 280,
      "nom": "Ville 280",
      "x": 0.8329752851974283,
      "y": 0.48454307891146764,
      "a": 924.3,
      "b": 1157.3,
      "service": 6.5
    },
    {
      "id": 281,
      "nom": "Ville 281",
      "x": 0.4671026282781843,
      "y": 0.04538805984571925,
      "a": 383.6,
      "b": 555.4,
      "service": 12.6
    },
    {
      "id": 282,
      "nom": "Ville 282",
      "x": 0.5102809227900958,
      "y": 0.7447476654547172,
      "a": 638.9,
      "b": 809.4,
      "service": 8.4
    },
    {
      "id": 283,
      "nom": "Ville 283",
      "x": 0.4225978111457399,
      "y": 0.3551773135885514,
      "a": 1108.4,
      "b": 1276.6,
      "service": 12.3
    },
    {
      "id": 284,
      "nom": "Ville 284",
      "x": 0.6568435388988518,
      "y": 0.01974138739808462,
      "a": 1174.1,
      "b": 1330.1,
      "service": 10.7
    },
    {
      "id": 285,
      "nom": "Ville 285",
      "x": 0.5071635969746414,
      "y": 0.9461270955326195,
      "a": 204.3,
      "b": 362.6,
      "service": 14.1
    },
    {
      "id": 286,
      "nom": "Ville 286",
      "x": 0.6904475919384765,
      "y": 0.40192372825721256,
      "a": 611.3,
      "b": 784.1,
      "service": 12.9
    },
    {
      "id": 287,
      "nom": "Ville 287",
      "x": 0.6889082362934618,
      "y": 0.6049939193159586,
      "a": 210.2,
      "b": 386.8,
      "service": 10.4
    },
    {
      "id": 288,
      "nom": "Ville 288",
      "x": 0.2088893914825677,
      "y": 0.2077083307298535,
      "a": 47.9,
      "b": 237.7,
      "service": 8.2
    },
    {
      "id": 289,
      "nom": "Ville 289",
      "x": 0.8860252896990286,
      "y": 0.2690692102056307,
      "a": 133.3,
      "b": 261.1,
      "service": 11.8
    },
    {
      "id": 290,
      "nom": "Ville 290",
      "x": 0.07488477751012912,
      "y": 0.8306775905962271,
      "a": 199.4,
      "b": 347.6,
      "service": 6.5
    },
    {
      "id": 291,
      "nom": "Ville 291",
      "x": 0.5231977675764631,
      "y": 0.3682081659729527,
      "a": 514.4,
      "b": 661.6,
      "service": 11.1
    },
    {
      "id": 292,
      "nom": "Ville 292",
      "x": 0.5115189221326331,
      "y": 0.7367256883512614,
      "a": 1004.2,
      "b": 1211.1,
      "service": 10.5
    },
    {
      "id": 293,
      "nom": "Ville 293",
      "x": 0.16855360788759777,
      "y": 0.6530669982365253,
      "a": 824.7,
      "b": 998.1,
      "service": 13.3
    },
    {
      "id": 294,
      "nom": "Ville 294",
      "x": 0.713436998399841,
      "y": 0.8150034439283779,
      "a": 350.2,
      "b": 572.1,
      "service": 11.2
    },
    {
      "id": 295,
      "nom": "Ville 295",
      "x": 0.26976063367613834,
      "y": 0.6096663306641944,
      "a": 999.9,
      "b": 1145.0,
      "service": 5.2
    },
    {
      "id": 296,
      "nom": "Ville 296",
      "x": 0.23211387837349717,
      "y": 0.5610446736195358,
      "a": 1075.3,
      "b": 1310.8,
      "service": 13.1
    },
    {
      "id": 297,
      "nom": "Ville 297",
      "x": 0.1723629719288945,
      "y": 0.7897676248812812,
      "a": 574.6,
      "b": 739.4,
      "service": 11.9
    },
    {
      "id": 298,
      "nom": "Ville 298",
      "x": 0.8667178646504996,
      "y": 0.32964356032052855,
      "a": 1213.4,
      "b": 1377.6,
      "service": 7.8
    },
    {
      "id": 299,
      "nom": "Ville 299",
      "x": 0.22231856181299336,
      "y": 0.9637884170558321,
      "a": 582.9,
      "b": 734.6,
      "service": 9.8
    },
    {
      "id": 300,
      "nom": "Ville 300",
      "x": 0.706690313251521,
      "y": 0.8437926222446576,
      "a": 1222.3,
      "b": 1414.9,
      "service": 11.5
    }
  ],
  "perturbations": [
    {
      "arc": [
        120,
        192
      ],
      "t_start": 268.2,
      "t_end": 349.7,
      "alpha": 1.73
    },
    {
      "arc": [
        24,
        237
      ],
      "t_start": 640.8,
      "t_end": 736.0,
      "alpha": 1.61
    },
    {
      "arc": [
        5,
        278
      ],
      "t_start": 371.2,
      "t_end": 679.0,
      "alpha": 2.88
    },
    {
      "arc": [
        19,
        126
      ],
      "t_start": 321.0,
      "t_end": 528.4,
      "alpha": 2.03
    },
    {
      "arc": [
        90,
        136
      ],
      "t_start": 642.1,
      "t_end": 935.5,
      "alpha": 1.74
    },
    {
      "arc": [
        157,
        242
      ],
      "t_start": 143.8,
      "t_end": 259.2,
      "alpha": 2.74
    },
    {
      "arc": [
        123,
        216
      ],
      "t_start": 267.8,
      "t_end": 458.0,
      "alpha": 2.56
    },
    {
      "arc": [
        102,
        215
      ],
      "t_start": 258.2,
      "t_end": 293.6,
      "alpha": 2.25
    },
    {
      "arc": [
        71,
        216
      ],
      "t_start": 279.6,
      "t_end": 511.8,
      "alpha": 1.73
    },
    {
      "arc": [
        50,
        175
      ],
      "t_start": 434.8,
      "t_end": 495.6,
      "alpha": 2.08
    },
    {
      "arc": [
        219,
        236
      ],
      "t_start": 292.6,
      "t_end": 482.2,
      "alpha": 2.76
    },
    {
      "arc": [
        6,
        209
      ],
      "t_start": 786.0,
      "t_end": 1043.4,
      "alpha": 2.55
    },
    {
      "arc": [
        25,
        58
      ],
      "t_start": 591.9,
      "t_end": 680.0,
      "alpha": 2.51
    },
    {
      "arc": [
        15,
        23
      ],
      "t_start": 634.0,
      "t_end": 846.8,
      "alpha": 2.18
    },
    {
      "arc": [
        3,
        82
      ],
      "t_start": 497.8,
      "t_end": 653.7,
      "alpha": 3.02
    },
    {
      "arc": [
        59,
        150
      ],
      "t_start": 316.9,
      "t_end": 507.2,
      "alpha": 3.44
    },
    {
      "arc": [
        33,
        249
      ],
      "t_start": 388.8,
      "t_end": 601.1,
      "alpha": 2.5
    },
    {
      "arc": [
        19,
        73
      ],
      "t_start": 63.6,
      "t_end": 181.2,
      "alpha": 2.54
    },
    {
      "arc": [
        150,
        290
      ],
      "t_start": 46.1,
      "t_end": 359.1,
      "alpha": 3.46
    },
    {
      "arc": [
        110,
        118
      ],
      "t_start": 492.2,
      "t_end": 872.8,
      "alpha": 3.02
    },
    {
      "arc": [
        9,
        140
      ],
      "t_start": 470.6,
      "t_end": 506.0,
      "alpha": 2.46
    },
    {
      "arc": [
        7,
        175
      ],
      "t_start": 705.6,
      "t_end": 898.1,
      "alpha": 3.36
    },
    {
      "arc": [
        12,
        278
      ],
      "t_start": 545.6,
      "t_end": 683.8,
      "alpha": 2.18
    },
    {
      "arc": [
        65,
        276
      ],
      "t_start": 260.3,
      "t_end": 603.9,
      "alpha": 2.53
    },
    {
      "arc": [
        76,
        236
      ],
      "t_start": 22.0,
      "t_end": 283.8,
      "alpha": 3.31
    },
    {
      "arc": [
        53,
        160
      ],
      "t_start": 212.9,
      "t_end": 330.0,
      "alpha": 2.04
    },
    {
      "arc": [
        115,
        148
      ],
      "t_start": 692.7,
      "t_end": 1008.9,
      "alpha": 1.97
    },
    {
      "arc": [
        70,
        175
      ],
      "t_start": 401.5,
      "t_end": 613.5,
      "alpha": 2.72
    },
    {
      "arc": [
        143,
        164
      ],
      "t_start": 133.1,
      "t_end": 459.3,
      "alpha": 2.03
    },
    {
      "arc": [
        0,
        2
      ],
      "t_start": 307.2,
      "t_end": 366.4,
      "alpha": 2.0
    }
  ]
}